{
  "checkpoint_path": "experiments/learner/recovery_q.pt",
  "num_episodes": 100,
  "final_reward_mean_last_10": 0.23204605988943738,
  "final_anc_mean_last_10": 0.6021724072534562,
  "num_updates": 70,
  "validation_history": [
    {
      "final_anc_mean": 0.9979224376731302,
      "final_anc_stderr": 0.0020355870438641325,
      "threshold_hit_mean": 1.0,
      "rounds_mean": 2.92,
      "episode": 20
    },
    {
      "final_anc_mean": 0.9279134760660472,
      "final_anc_stderr": 0.04244583185406345,
      "threshold_hit_mean": 0.92,
      "rounds_mean": 3.0,
      "episode": 40
    },
    {
      "final_anc_mean": 0.8583192080830162,
      "final_anc_stderr": 0.057556816052179646,
      "threshold_hit_mean": 0.84,
      "rounds_mean": 3.2,
      "episode": 60
    },
    {
      "final_anc_mean": 0.9016998326151714,
      "final_anc_stderr": 0.05582178434572377,
      "threshold_hit_mean": 0.88,
      "rounds_mean": 2.92,
      "episode": 80
    },
    {
      "final_anc_mean": 0.9317205280920785,
      "final_anc_stderr": 0.03562797988767689,
      "threshold_hit_mean": 0.88,
      "rounds_mean": 3.24,
      "episode": 100
    }
  ]
}